setup.py
data_helper_2/__init__.py
data_helper_2/data_helper.py
data_helper_2/visualisation.py
data_helper_2.egg-info/PKG-INFO
data_helper_2.egg-info/SOURCES.txt
data_helper_2.egg-info/dependency_links.txt
data_helper_2.egg-info/not-zip-safe
data_helper_2.egg-info/requires.txt
data_helper_2.egg-info/top_level.txt