Metadata-Version: 1.0
Name: data-helper-2
Version: 0.2
Summary: A helper containing methods to aid visualisation and preliminary analysis of data
Home-page: http://github.com/karthickrajas/data_helper
Author: Karthick Raja
Author-email: karthick11b36@gmail.com
License: MIT
Platform: UNKNOWN
